molgenis/api_support.py
molgenis/client.py
molgenis/errors.py
molgenis/query_utils.py
molgenis/utils.py
molgenis_py_client-2.4.1.dist-info/LICENSE
molgenis_py_client-2.4.1.dist-info/METADATA
molgenis_py_client-2.4.1.dist-info/WHEEL
molgenis_py_client-2.4.1.dist-info/top_level.txt
molgenis_py_client-2.4.1.dist-info/RECORD
