Metadata-Version: 2.1
Name: molgenis-py-client
Version: 2.4.1
Summary: The Python client for the MOLGENIS REST API
Home-page: https://github.com/molgenis/molgenis-py-client/
License: GNU Lesser General Public License 3.0
Platform: UNKNOWN
Requires-Python: >=3.6
Requires-Dist: requests (>=2.21.0)
